Makefile
README.rst
setup.py
docs/Makefile
docs/make.bat
docs/source/HISTORY.rst
docs/source/README.rst
docs/source/api.rst
docs/source/conf.py
docs/source/index.rst
scripts/api-sample.py
scripts/out.txt
scripts/sample.zip
xmldirector/__init__.py
xmldirector.facebook.egg-info/PKG-INFO
xmldirector.facebook.egg-info/SOURCES.txt
xmldirector.facebook.egg-info/dependency_links.txt
xmldirector.facebook.egg-info/entry_points.txt
xmldirector.facebook.egg-info/namespace_packages.txt
xmldirector.facebook.egg-info/not-zip-safe
xmldirector.facebook.egg-info/requires.txt
xmldirector.facebook.egg-info/top_level.txt
xmldirector/facebook/__init__.py
xmldirector/facebook/configure.zcml
xmldirector/facebook/header.txt
xmldirector/facebook/i18n.py
xmldirector/facebook/interfaces.py
xmldirector/facebook/logger.py
xmldirector/facebook/browser/__init__.py
xmldirector/facebook/browser/configure.zcml
xmldirector/facebook/browser/controlpanel.py
xmldirector/facebook/browser/facebook.pt
xmldirector/facebook/browser/fb.py
xmldirector/facebook/locales/LC_MESSAGES/de/README.txt
xmldirector/facebook/profiles/default/README.txt
xmldirector/facebook/profiles/default/browserlayer.xml
xmldirector/facebook/profiles/default/controlpanel.xml
xmldirector/facebook/profiles/default/metadata.xml
xmldirector/facebook/profiles/default/registry.xml
xmldirector/facebook/profiles/default/types.xml
xmldirector/facebook/profiles/default/types/xmldirector.plonecore.connector.xml